nonebot_plugin_maimaimonitor/__init__.py
nonebot_plugin_maimaimonitor/client.py
nonebot_plugin_maimaimonitor/config.py
nonebot_plugin_maimaimonitor/constants.py
nonebot_plugin_maimaimonitor/maimai_plugin_v11.py
nonebot_plugin_maimaimonitor-1.9.18.dist-info/licenses/LICENSE
nonebot_plugin_maimaimonitor-1.9.18.dist-info/METADATA
nonebot_plugin_maimaimonitor-1.9.18.dist-info/WHEEL
nonebot_plugin_maimaimonitor-1.9.18.dist-info/top_level.txt
nonebot_plugin_maimaimonitor-1.9.18.dist-info/RECORD
