Metadata-Version: 2.4
Name: nonebot-plugin-maimaimonitor
Version: 1.9.18
Summary: A NoneBot2 plugin to report maimai server status.
Author: Chongxi3555
License-Expression: MIT
Project-URL: Homepage, https://github.com/ChongxiSama/nonebot-plugin-maimaimonitor
Project-URL: Repository, https://github.com/ChongxiSama/nonebot-plugin-maimaimonitor
Requires-Python: >=3.8
License-File: LICENSE
Requires-Dist: nonebot2>=2.0.0
Requires-Dist: nonebot-adapter-onebot>=2.0.0
Requires-Dist: nonebot-plugin-apscheduler>=0.3.0
Requires-Dist: httpx>=0.20.0
Dynamic: license-file
